{
  "db_name": "PostgreSQL",
  "query": "\n            INSERT INTO posts (title, content, author_id)\n            VALUES ($1, $2, $3)\n            RETURNING id, title as \"title!\", content, author_id, created_at, updated_at\n            ",
  "describe": {
    "columns": [
      {
        "ordinal": 0,
        "name": "id",
        "type_info": "Int8"
      },
      {
        "ordinal": 1,
        "name": "title!",
        "type_info": "Varchar"
      },
      {
        "ordinal": 2,
        "name": "content",
        "type_info": "Text"
      },
      {
        "ordinal": 3,
        "name": "author_id",
        "type_info": "Int8"
      },
      {
        "ordinal": 4,
        "name": "created_at",
        "type_info": "Timestamptz"
      },
      {
        "ordinal": 5,
        "name": "updated_at",
        "type_info": "Timestamptz"
      }
    ],
    "parameters": {
      "Left": [
        "Varchar",
        "Text",
        "Int8"
      ]
    },
    "nullable": [
      false,
      false,
      false,
      false,
      false,
      false
    ]
  },
  "hash": "9e03077e207413290d59f273519411adb63d184f9e7b46d4bbf70dff2dbfc658"
}
